LICENSE
bodhiext/cohere/__init__.py
bodhiext/cohere/_cohere.py
bodhiext/cohere/_version.py
bodhiext_cohere-0.1.0.dist-info/LICENSE
bodhiext_cohere-0.1.0.dist-info/METADATA
bodhiext_cohere-0.1.0.dist-info/WHEEL
bodhiext_cohere-0.1.0.dist-info/entry_points.txt
bodhiext_cohere-0.1.0.dist-info/RECORD
