Metadata-Version: 2.1
Name: bodhiext.cohere
Version: 0.1.0
Summary: Bohilib plugin for Cohere by bodhiext
License: MIT
Requires-Python: >=3.8.1,<3.12
Classifier: License :: OSI Approved :: MIT License
Classifier: Programming Language :: Python :: 3
Classifier: Programming Language :: Python :: 3.9
Classifier: Programming Language :: Python :: 3.10
Classifier: Programming Language :: Python :: 3.11
Requires-Dist: bodhilib (>=0.1.9,<0.2.0)
Requires-Dist: cohere (>=4.21,<5.0)
Requires-Dist: pydantic (>=1,<2)
